dataflow/__init__.py
dataflow/utils.py
dataflow/analysis/__init__.py
dataflow/analysis/base.py
dataflow/analysis/textual.py
dataflow/mutations/__init__.py
dataflow/mutations/creators.py
dataflow/mutations/decorators.py
dataflow/mutations/mutations.py
dataflow/mutations/types.py
dataflow/mutations/formatters/__init__.py
dataflow/mutations/formatters/common.py
dataflow/mutations/formatters/dto.py
dataflow/mutations/formatters/types.py
dataflow/validations/__init__.py
dataflow/validations/decorators.py
dataflow/validations/dto.py
dataflow/validations/errors.py
dataflow/validations/types.py
dataflow/validations/validations.py
dataflow/validations/failure_handlers/__init__.py
dataflow/validations/failure_handlers/common.py
dataflow/validations/pipelines/__init__.py
dataflow/validations/pipelines/after.py
dataflow/validations/pipelines/before.py
dataflow/validations/pipelines/during.py
python_dataflow-0.0.1.dist-info/licenses/LICENSE.md
python_dataflow-0.0.1.dist-info/METADATA
python_dataflow-0.0.1.dist-info/WHEEL
python_dataflow-0.0.1.dist-info/top_level.txt
python_dataflow-0.0.1.dist-info/RECORD
