Metadata-Version: 2.4
Name: python-dataflow
Version: 0.0.1
Summary: Pipelines validations with simple decorators
Author-email: Andrey Ivanov <python.on.papyrus@gmail.com>
License: MIT
Project-URL: Homepage, https://github.com/knucklesuganda/dataflow
Keywords: pipelines,validation,dataflow,mutations,decorators,data science
Platform: UNKNOWN
Classifier: Programming Language :: Python :: 3
Classifier: License :: OSI Approved :: MIT License
Classifier: Operating System :: OS Independent
Requires-Python: >=3.9
License-File: LICENSE.md
Requires-Dist: colorama>=0.4.6
Requires-Dist: Faker>=13.3.4
Dynamic: license-file
